main.v
module vending_machine(
    input clk,
    input rst,
    input [1:0]in,
    output reg out,
    output reg [1:0] change,
    output reg [1:0] c_state,
    output reg [1:0] n_state
   );

parameter s0 = 2'b00;
parameter s1 = 2'b01;
parameter s2 = 2'b10;

    //reg [1:0] c_state, n_state;

    always @(posedge clk )
      begin
        
        if (rst ==1)
         begin
           c_state =0;
           n_state =0;
           change = 2'b00; 
        end
        else
          c_state = n_state;
        
        case (c_state)
            s0: //state 0 : 0 rs
            if (in == 2'b00)
              begin
                n_state = s0; //stay in state 0
                out = 0; //no item dispensed
                change = 2'b00; //no change
              end 
            else if (in == 2'b01) //5 rs inserted
              begin
                n_state = s1; //move to state 1
                out = 0; //no item dispensed
                change = 2'b00; //no change
              end 
            else if (in == 2'b10) //10 rs inserted
              begin
                n_state = s2; //move to state 2
                out = 0; //no item dispensed
                change = 2'b00; //no change
              end 
            s1: //state 1 : 5 rs
               if (in == 2'b00)
                begin
                    n_state = s0;
                    out = 0; //no item dispensed
                    change = 2'b01; // change returned 5 rs
                end
                else if (in == 2'b01) 
                begin
                    n_state = s2; 
                    out = 0; //no item dispensed
                    change = 2'b00; //no change
                end
                else if (in == 2'b10)
                begin
                    n_state = s0;
                    out = 1; // item dispensed
                    change = 2'b00; //no change
                end
            s2: //state 2 : 10 rs
                if (in == 2'b00)
                begin
                    n_state = s0;
                    out = 0; //no item dispensed
                    change = 2'b10; // change returned 10 rs
                end
                else if (in == 2'b01)
                begin
                    n_state = s0; 
                    out = 1; // item dispensed
                    change = 2'b00; //no change
                end
                else if (in == 2'b10)
                begin
                    n_state = s0; 
                    out = 1; // item dispensed
                    change = 2'b01; // change returned 5rs and one bottle
                end

        endcase
        end
endmodule

test1.v
module vending_machine_tb;
    // inputs
    reg clk;
    reg rst;
    reg [1:0] in;

    // outputs
    wire out;   
    wire [1:0] change;
    wire [1:0] c_state;
    wire [1:0] n_state;

    vending_machine uut (
        .clk(clk),
        .rst(rst),
        .in(in),
        .out(out),
        .change(change),
        .c_state(c_state),
        .n_state(n_state)
    );

    initial begin
        // Initialize inputs
        $dumpfile("vending_machine.vcd");
        $dumpvars(1,vending_machine_tb, uut);
        clk = 0;
        rst = 1;

        #6 rst = 0; 
        in = 1;
        #11 in = 1;
        #16 in = 1;
        #25 $finish;

    end
    always #5 clk = ~clk; // Clock generation

endmodule

vending_machine.vcd
$date
	Sun Jun 22 13:06:48 2025
$end
$version
	Icarus Verilog
$end
$timescale
	1s
$end
$scope module vending_machine_tb $end
$var wire 1 ! out $end
$var wire 2 " n_state [1:0] $end
$var wire 2 # change [1:0] $end
$var wire 2 $ c_state [1:0] $end
$var reg 1 % clk $end
$var reg 2 & in [1:0] $end
$var reg 1 ' rst $end
$upscope $end
$scope module vending_machine_tb $end
$scope module uut $end
$var wire 1 % clk $end
$var wire 2 ( in [1:0] $end
$var wire 1 ' rst $end
$var parameter 2 ) s0 $end
$var parameter 2 * s1 $end
$var parameter 2 + s2 $end
$var reg 2 , c_state [1:0] $end
$var reg 2 - change [1:0] $end
$var reg 2 . n_state [1:0] $end
$var reg 1 ! out $end
$upscope $end
$upscope $end
$enddefinitions $end
$comment Show the parameter values. $end
$dumpall
b10 +
b1 *
b0 )
$end
#0
$dumpvars
bx .
bx -
bx ,
bx (
1'
bx &
0%
bx $
bx #
bx "
x!
$end
#5
b0 #
b0 -
b0 "
b0 .
b0 $
b0 ,
1%
#6
b1 &
b1 (
0'
#10
0%
#15
0!
b1 "
b1 .
1%
#20
0%
#25
b10 "
b10 .
b1 $
b1 ,
1%
#30
0%
#35
1!
b0 "
b0 .
b10 $
b10 ,
1%
#40
0%
#45
0!
b1 "
b1 .
b0 $
b0 ,
1%
#50
0%
#55
b10 "
b10 .
b1 $
b1 ,
1%
